MANIFEST.in
README.rst
requirements.txt
setup.py
version.py
doublex/__init__.py
doublex/doubles.py
doublex/internal.py
doublex/matchers.py
doublex/proxy.py
doublex/py27_backports.py
doublex/safeunicode.py
doublex/tracer.py
doublex.egg-info/PKG-INFO
doublex.egg-info/SOURCES.txt
doublex.egg-info/dependency_links.txt
doublex.egg-info/requires.txt
doublex.egg-info/top_level.txt